reading_gist/__init__.py
reading_gist/module1.py
tests/__init__.py
tests/test_module1.py
reading_gist-0.0.4.dist-info/LICENSE.txt
reading_gist-0.0.4.dist-info/METADATA
reading_gist-0.0.4.dist-info/WHEEL
reading_gist-0.0.4.dist-info/top_level.txt
reading_gist-0.0.4.dist-info/RECORD
